CRISP/__init__.py
CRISP/_version.py
CRISP/cli.py
CRISP/py.typed
CRISP/data/wrapped_traj.traj
CRISP/data_analysis/__init__.py
CRISP/data_analysis/clustering.py
CRISP/data_analysis/contact_coordination.py
CRISP/data_analysis/h_bond.py
CRISP/data_analysis/msd.py
CRISP/data_analysis/prdf.py
CRISP/data_analysis/volumetric_atomic_density.py
CRISP/simulation_utility/__init__.py
CRISP/simulation_utility/atomic_indices.py
CRISP/simulation_utility/atomic_traj_linemap.py
CRISP/simulation_utility/error_analysis.py
CRISP/simulation_utility/interatomic_distances.py
CRISP/simulation_utility/subsampling.py
CRISP/tests/__init__.py
CRISP/tests/test_CRISP.py
CRISP/tests/test_cli.py
CRISP/tests/test_crisp_comprehensive.py
CRISP/tests/DataAnalysis/__init__.py
CRISP/tests/DataAnalysis/test_clustering_extended.py
CRISP/tests/DataAnalysis/test_contact_coordination.py
CRISP/tests/DataAnalysis/test_contact_coordination_extended.py
CRISP/tests/DataAnalysis/test_h_bond_complete.py
CRISP/tests/DataAnalysis/test_h_bond_extended.py
CRISP/tests/DataAnalysis/test_msd_complete.py
CRISP/tests/DataAnalysis/test_msd_extended.py
CRISP/tests/DataAnalysis/test_prdf.py
CRISP/tests/DataAnalysis/test_volumetric_atomic_density.py
CRISP/tests/SimulationUtility/__init__.py
CRISP/tests/SimulationUtility/test_atomic_traj_linemap.py
CRISP/tests/SimulationUtility/test_atomic_traj_linemap_extended.py
CRISP/tests/SimulationUtility/test_error_analysis_extended.py
CRISP/tests/SimulationUtility/test_interatomic_distances.py
CRISP/tests/SimulationUtility/test_subsampling.py
crisp_ase-1.1.4.dist-info/licenses/LICENSE
crisp_ase-1.1.4.dist-info/METADATA
crisp_ase-1.1.4.dist-info/WHEEL
crisp_ase-1.1.4.dist-info/entry_points.txt
crisp_ase-1.1.4.dist-info/top_level.txt
crisp_ase-1.1.4.dist-info/RECORD
