Metadata-Version: 2.4
Name: crisp-ase
Version: 1.1.4
Author-email: IS <indranilsaha15@gmail.com>
License-Expression: CC-BY-NC-SA-4.0
License-File: LICENSE
Requires-Dist: numpy<2.3,>=1.24
Requires-Dist: ase
Requires-Dist: fpsample<1.0,>=0.3.3
Requires-Dist: seaborn>=0.12.2
Requires-Dist: dscribe>=2.0.0
Requires-Dist: matplotlib>=3.3.4
Requires-Dist: joblib>=1.0.0
Requires-Dist: scikit-learn>=1.0.0
Requires-Dist: plotly>=5.9.0
Requires-Dist: pandas>=2.0.3
Requires-Dist: networkx>=3.1
Requires-Dist: statsmodels>=0.14.0
Provides-Extra: test
Requires-Dist: pytest>=6.1.2; extra == "test"
Dynamic: license-file
